mmobs_logger/__init__.py
mmobs_logger/ui.py
mmobs_logger-0.2.dist-info/METADATA
mmobs_logger-0.2.dist-info/WHEEL
mmobs_logger-0.2.dist-info/top_level.txt
mmobs_logger-0.2.dist-info/RECORD
