Metadata-Version: 2.1
Name: mmobs-logger
Version: 0.2
Summary: Python software to generate a user interface for marine mammal observation logging and GPS tracking for visual surveys of marine mammal abundance.
Home-page: https://zenodo.org/doi/10.5281/zenodo.10228669
Author: Sebastian Menze
Author-email: sebastian.menze@gmail.com
Classifier: Programming Language :: Python :: 3.9
Requires-Dist: PyQt5
Requires-Dist: pynmea2
Requires-Dist: pyserial
Requires-Dist: pandas
